smak/.DS_Store
smak/AdvancedFilteringClass.py
smak/AlignStack3.py
smak/BatchAnalyze.py
smak/BatchDisplay.py
smak/BatchMode.py
smak/BatchProcess.py
smak/BeamDeconvolutionClass.py
smak/ChannelInterpret.py
smak/ConcentrationStandardClass.py
smak/CorrelationPlotClass.py
smak/CustomKernelClass.py
smak/DataAveragingClass.py
smak/DataSummaryClass.py
smak/Deconv.py
smak/Display.py
smak/ExportRegistrationClass.py
smak/FFTtomo.py
smak/FaderClass.py
smak/FileTracker.py
smak/FittingFunctions.py
smak/IR_MathClass.py
smak/ImCmap.py
smak/ImRadon.py
smak/ImageGet.py
smak/LAMSImageGet.py
smak/MCAImageGet.py
smak/MakeHistogramClass.py
smak/Mask.py
smak/MasterClass.py
smak/MathWindowClass.py
smak/MomentAnalysisClass.py
smak/MomentMathClass.py
smak/MultiFitObj.py
smak/MultiMassCalibrationClass.py
smak/MyGraph.py
smak/NNLS.py
smak/PCAAnalysisClass.py
smak/PCAAnalysisMathClass.py
smak/ParticleStatisticsClass.py
smak/PmwTtkButtonBox.py
smak/PmwTtkMenuBar.py
smak/PmwTtkNoteBook.py
smak/PmwTtkRadioSelect.py
smak/QuantThicknessDialog.py
smak/RadialProfileClass.py
smak/RegistrationCNN.py
smak/ScrollTree.py
smak/SortedCollection.py
smak/ThresholdingClass.py
smak/TomoRecon.py
smak/TriColorWindowClass.py
smak/VGG16.py
smak/WeightedGroupPCA.py
smak/XanesFitClass.py
smak/__main__.py
smak/absorptionCalc.py
smak/align_images.py
smak/atomic_sub.py
smak/batchCommands.json
smak/ciexyz.py
smak/colormaps.txt
smak/colormodels.py
smak/congrid.py
smak/desktop.ini
smak/func.py
smak/globalfuncs.py
smak/histclass.py
smak/imgFuse.py
smak/mcatemp.hdf5
smak/mucal.py
smak/oospec_calibration.txt
smak/parseFormula.py
smak/pyMcaFitWrapper.py
smak/pyMcaMaterials.py
smak/pyMcaParamGUI.py
smak/read_agilent.py
smak/screencapture.py
smak/sivm.py
smak/smak.icns
smak/smak.ico
smak/smak.py
smak/smak_sm.jpg
smak/smwPmw.py
smak/spline.py
smak/stitch_hdf_mod.py
smak/tkFileDialogDir.py
smak/varimax.py
smak/__pycache__/AdvancedFilteringClass.cpython-38.pyc
smak/__pycache__/BatchAnalyze.cpython-38.pyc
smak-3.0.11.dist-info/LICENSE
smak-3.0.11.dist-info/METADATA
smak-3.0.11.dist-info/WHEEL
smak-3.0.11.dist-info/top_level.txt
smak-3.0.11.dist-info/RECORD
