Metadata-Version: 2.1
Name: smak
Version: 3.0.11
Summary: A MicroAnalysis Toolkit.
Author-email: Sam Webb <samwebb@slac.stanford.edu>
Project-URL: Homepage, https://www.sams-xrays.com/install-smak
Project-URL: Bug Tracker, https://www.sams-xrays.com/forum
Classifier: Programming Language :: Python :: 3
Classifier: License :: OSI Approved :: MIT License
Classifier: Operating System :: OS Independent
Requires-Python: <3.11,>=3.7
License-File: LICENSE
Requires-Dist: pyimzml
Requires-Dist: PyQt5
Requires-Dist: opusFC
Requires-Dist: Pmw >=2.1.1
Requires-Dist: numpy ==1.26.4
Requires-Dist: pandas
Requires-Dist: PyWavelets
Requires-Dist: scikit-image
Requires-Dist: scikit-learn
Requires-Dist: fabio
Requires-Dist: spectral
Requires-Dist: pymca ==5.9.0
Requires-Dist: imreg-dft
Requires-Dist: pyscreenshot
Requires-Dist: imutils
Requires-Dist: opencv-python
Requires-Dist: sortedcontainers
Requires-Dist: dill
Requires-Dist: scipy ==1.12.0
Requires-Dist: tifffile ==2021.7.2
Requires-Dist: pyometiff
Requires-Dist: renishawWiRE
Requires-Dist: pymatreader
Requires-Dist: statsmodels
